{
  "step": 12,
  "url": "https://www.ebay.com/lstng?draftId=5182232721813&mode=AddItem",
  "title": "List an item | eBay",
  "page_summary": "",
  "memory": "I have successfully identified and documented all major sections of the eBay listing creation page, including Photos & Video, Title, Item Category, Item Specifics, Description, Pricing, Delivery, and Final Actions. I have also identified the final publish button as \"List it\" and noted various dropdown options and popups.",
  "next_goal": "",
  "actions": [
    {
      "done": {
        "text": "I have documented every field, button, and interactive element on the eBay listing creation page. \n\n1. **URL:** https://www.ebay.com/lstng?draftId=5182232721813&mode=AddItem\n2. **Interactive Elements:**\n   - **Photos & Video:** 'Photo tips' button, 'Upload from computer', 'Upload from mobile', and image placeholders (Required).\n   - **Title:** 'Item title' input field (Required).\n   - **Item category:** 'Edit' button.\n   - **Item specifics (Required):** 'Brand' (Nike), 'US Shoe Size' (3-20), 'Color' (Beige to Yellow), 'Department' (Men, Teens, Unisex).\n   - **Item specifics (Additional):** 'Customized', 'Style Code', 'UK Shoe Size', 'Product Line', 'Model', 'Country of Origin', and 'Show more' button.\n   - **Description:** Rich text editor with Font Family, Font Size, Bold, Underline, 'Show HTML Code', and 'Use AI description' button.\n   - **Pricing:** Format toggle (Buy It Now/Auction), 'Item price' (Required), 'Quantity', 'Allow offers' switch, and 'Schedule your listing' switch.\n   - **Delivery:** Shipping Method (Shipping or pickup, etc.), 'View all shipping services', 'Who pays?' (Buyer/Seller pays), 'Edit shipping cost', 'Handling time' (Same day to 3 days).\n   - **Final Actions:** 'Edit' (Charity), 'List it' (Publish button), 'Save for later', and 'Preview'.\n3. **Sections:** Photos & Video, Title, Item category, Item specifics, Description, Pricing, Delivery, Charity.\n4. **Publish Button:** The final button is labeled 'List it'.\n5. **Popups/Blockers:** 'Photo tips' popup and 'Delivery details' edit window were identified. No login prompts or blockers were encountered on this page.",
        "success": true,
        "files_to_display": []
      }
    }
  ]
}